[{
		"id": 51,
		"type": "door",
		"imgS": "",
		"imgL": "51.png",
		"degree": "",
		"name": "",
		"engName": "",
		"desc": "",
		"effect": "",
		"badStuff": "",
		"fightLevel": "",
		"reward": "",
		"class": "",
		"family": "",
		"lootSize": "",
		"lootType": "",
		"weaponType": "",
		"cost": "",
		"speciesRestriction": "",
		"damageKeys": "",
		"organicOrSynth": "",
		"skillType": "",
		"skillRank": "",
		"artAuthor": "",
		"artSource": "",
		"authorUrl": "",
		"sourceUrl": ""
	},
	{
		"id": 52,
		"type": "door",
		"imgS": "",
		"imgL": "52.png",
		"degree": "",
		"name": "",
		"engName": "",
		"desc": "",
		"effect": "",
		"badStuff": "",
		"fightLevel": "",
		"reward": "",
		"class": "",
		"family": "",
		"lootSize": "",
		"lootType": "",
		"weaponType": "",
		"cost": "",
		"speciesRestriction": "",
		"damageKeys": "",
		"organicOrSynth": "",
		"skillType": "",
		"skillRank": "",
		"artAuthor": "",
		"artSource": "",
		"authorUrl": "",
		"sourceUrl": ""
	},
	{
		"id": 53,
		"type": "door",
		"imgS": "",
		"imgL": "53.png",
		"degree": "",
		"name": "",
		"engName": "",
		"desc": "",
		"effect": "",
		"badStuff": "",
		"fightLevel": "",
		"reward": "",
		"class": "",
		"family": "",
		"lootSize": "",
		"lootType": "",
		"weaponType": "",
		"cost": "",
		"speciesRestriction": "",
		"damageKeys": "",
		"organicOrSynth": "",
		"skillType": "",
		"skillRank": "",
		"artAuthor": "",
		"artSource": "",
		"authorUrl": "",
		"sourceUrl": ""
	},
	{
		"id": 54,
		"type": "door",
		"imgS": "",
		"imgL": "54.png",
		"degree": "",
		"name": "",
		"engName": "",
		"desc": "",
		"effect": "",
		"badStuff": "",
		"fightLevel": "",
		"reward": "",
		"class": "",
		"family": "",
		"lootSize": "",
		"lootType": "",
		"weaponType": "",
		"cost": "",
		"speciesRestriction": "",
		"damageKeys": "",
		"organicOrSynth": "",
		"skillType": "",
		"skillRank": "",
		"artAuthor": "",
		"artSource": "",
		"authorUrl": "",
		"sourceUrl": ""
	},
	{
		"id": 55,
		"type": "door",
		"imgS": "",
		"imgL": "55.png",
		"degree": "",
		"name": "",
		"engName": "",
		"desc": "",
		"effect": "",
		"badStuff": "",
		"fightLevel": "",
		"reward": "",
		"class": "",
		"family": "",
		"lootSize": "",
		"lootType": "",
		"weaponType": "",
		"cost": "",
		"speciesRestriction": "",
		"damageKeys": "",
		"organicOrSynth": "",
		"skillType": "",
		"skillRank": "",
		"artAuthor": "",
		"artSource": "",
		"authorUrl": "",
		"sourceUrl": ""
	},
	{
		"id": 56,
		"type": "door",
		"imgS": "",
		"imgL": "56.png",
		"degree": "",
		"name": "",
		"engName": "",
		"desc": "",
		"effect": "",
		"badStuff": "",
		"fightLevel": "",
		"reward": "",
		"class": "",
		"family": "",
		"lootSize": "",
		"lootType": "",
		"weaponType": "",
		"cost": "",
		"speciesRestriction": "",
		"damageKeys": "",
		"organicOrSynth": "",
		"skillType": "",
		"skillRank": "",
		"artAuthor": "",
		"artSource": "",
		"authorUrl": "",
		"sourceUrl": ""
	},
	{
		"id": 57,
		"type": "door",
		"imgS": "",
		"imgL": "57.png",
		"degree": "",
		"name": "",
		"engName": "",
		"desc": "",
		"effect": "",
		"badStuff": "",
		"fightLevel": "",
		"reward": "",
		"class": "",
		"family": "",
		"lootSize": "",
		"lootType": "",
		"weaponType": "",
		"cost": "",
		"speciesRestriction": "",
		"damageKeys": "",
		"organicOrSynth": "",
		"skillType": "",
		"skillRank": "",
		"artAuthor": "",
		"artSource": "",
		"authorUrl": "",
		"sourceUrl": ""
	},
	{
		"id": 58,
		"type": "door",
		"imgS": "",
		"imgL": "58.png",
		"degree": "",
		"name": "",
		"engName": "",
		"desc": "",
		"effect": "",
		"badStuff": "",
		"fightLevel": "",
		"reward": "",
		"class": "",
		"family": "",
		"lootSize": "",
		"lootType": "",
		"weaponType": "",
		"cost": "",
		"speciesRestriction": "",
		"damageKeys": "",
		"organicOrSynth": "",
		"skillType": "",
		"skillRank": "",
		"artAuthor": "",
		"artSource": "",
		"authorUrl": "",
		"sourceUrl": ""
	},
	{
		"id": 59,
		"type": "door",
		"imgS": "",
		"imgL": "59.png",
		"degree": "",
		"name": "",
		"engName": "",
		"desc": "",
		"effect": "",
		"badStuff": "",
		"fightLevel": "",
		"reward": "",
		"class": "",
		"family": "",
		"lootSize": "",
		"lootType": "",
		"weaponType": "",
		"cost": "",
		"speciesRestriction": "",
		"damageKeys": "",
		"organicOrSynth": "",
		"skillType": "",
		"skillRank": "",
		"artAuthor": "",
		"artSource": "",
		"authorUrl": "",
		"sourceUrl": ""
	},
	{
		"id": 60,
		"type": "door",
		"imgS": "",
		"imgL": "60.png",
		"degree": "",
		"name": "",
		"engName": "",
		"desc": "",
		"effect": "",
		"badStuff": "",
		"fightLevel": "",
		"reward": "",
		"class": "",
		"family": "",
		"lootSize": "",
		"lootType": "",
		"weaponType": "",
		"cost": "",
		"speciesRestriction": "",
		"damageKeys": "",
		"organicOrSynth": "",
		"skillType": "",
		"skillRank": "",
		"artAuthor": "",
		"artSource": "",
		"authorUrl": "",
		"sourceUrl": ""
	},
	{
		"id": 131,
		"type": "door",
		"imgS": "",
		"imgL": "131.png",
		"degree": "",
		"name": "",
		"engName": "",
		"desc": "",
		"effect": "",
		"badStuff": "",
		"fightLevel": "",
		"reward": "",
		"class": "",
		"family": "",
		"lootSize": "",
		"lootType": "",
		"weaponType": "",
		"cost": "",
		"speciesRestriction": "",
		"damageKeys": "",
		"organicOrSynth": "",
		"skillType": "",
		"skillRank": "",
		"artAuthor": "",
		"artSource": "",
		"authorUrl": "",
		"sourceUrl": ""
	},
	{
		"id": 132,
		"type": "door",
		"imgS": "",
		"imgL": "132.png",
		"degree": "",
		"name": "",
		"engName": "",
		"desc": "",
		"effect": "",
		"badStuff": "",
		"fightLevel": "",
		"reward": "",
		"class": "",
		"family": "",
		"lootSize": "",
		"lootType": "",
		"weaponType": "",
		"cost": "",
		"speciesRestriction": "",
		"damageKeys": "",
		"organicOrSynth": "",
		"skillType": "",
		"skillRank": "",
		"artAuthor": "",
		"artSource": "",
		"authorUrl": "",
		"sourceUrl": ""
	},
	{
		"id": 133,
		"type": "door",
		"imgS": "",
		"imgL": "133.png",
		"degree": "",
		"name": "",
		"engName": "",
		"desc": "",
		"effect": "",
		"badStuff": "",
		"fightLevel": "",
		"reward": "",
		"class": "",
		"family": "",
		"lootSize": "",
		"lootType": "",
		"weaponType": "",
		"cost": "",
		"speciesRestriction": "",
		"damageKeys": "",
		"organicOrSynth": "",
		"skillType": "",
		"skillRank": "",
		"artAuthor": "",
		"artSource": "",
		"authorUrl": "",
		"sourceUrl": ""
	},
	{
		"id": 134,
		"type": "door",
		"imgS": "",
		"imgL": "134.png",
		"degree": "",
		"name": "",
		"engName": "",
		"desc": "",
		"effect": "",
		"badStuff": "",
		"fightLevel": "",
		"reward": "",
		"class": "",
		"family": "",
		"lootSize": "",
		"lootType": "",
		"weaponType": "",
		"cost": "",
		"speciesRestriction": "",
		"damageKeys": "",
		"organicOrSynth": "",
		"skillType": "",
		"skillRank": "",
		"artAuthor": "",
		"artSource": "",
		"authorUrl": "",
		"sourceUrl": ""
	},
	{
		"id": 135,
		"type": "door",
		"imgS": "",
		"imgL": "135.png",
		"degree": "",
		"name": "",
		"engName": "",
		"desc": "",
		"effect": "",
		"badStuff": "",
		"fightLevel": "",
		"reward": "",
		"class": "",
		"family": "",
		"lootSize": "",
		"lootType": "",
		"weaponType": "",
		"cost": "",
		"speciesRestriction": "",
		"damageKeys": "",
		"organicOrSynth": "",
		"skillType": "",
		"skillRank": "",
		"artAuthor": "",
		"artSource": "",
		"authorUrl": "",
		"sourceUrl": ""
	},
	{
		"id": 136,
		"type": "door",
		"imgS": "",
		"imgL": "136.png",
		"degree": "",
		"name": "",
		"engName": "",
		"desc": "",
		"effect": "",
		"badStuff": "",
		"fightLevel": "",
		"reward": "",
		"class": "",
		"family": "",
		"lootSize": "",
		"lootType": "",
		"weaponType": "",
		"cost": "",
		"speciesRestriction": "",
		"damageKeys": "",
		"organicOrSynth": "",
		"skillType": "",
		"skillRank": "",
		"artAuthor": "",
		"artSource": "",
		"authorUrl": "",
		"sourceUrl": ""
	},
	{
		"id": 137,
		"type": "door",
		"imgS": "",
		"imgL": "137.png",
		"degree": "",
		"name": "",
		"engName": "",
		"desc": "",
		"effect": "",
		"badStuff": "",
		"fightLevel": "",
		"reward": "",
		"class": "",
		"family": "",
		"lootSize": "",
		"lootType": "",
		"weaponType": "",
		"cost": "",
		"speciesRestriction": "",
		"damageKeys": "",
		"organicOrSynth": "",
		"skillType": "",
		"skillRank": "",
		"artAuthor": "",
		"artSource": "",
		"authorUrl": "",
		"sourceUrl": ""
	},
	{
		"id": 138,
		"type": "door",
		"imgS": "",
		"imgL": "138.png",
		"degree": "",
		"name": "",
		"engName": "",
		"desc": "",
		"effect": "",
		"badStuff": "",
		"fightLevel": "",
		"reward": "",
		"class": "",
		"family": "",
		"lootSize": "",
		"lootType": "",
		"weaponType": "",
		"cost": "",
		"speciesRestriction": "",
		"damageKeys": "",
		"organicOrSynth": "",
		"skillType": "",
		"skillRank": "",
		"artAuthor": "",
		"artSource": "",
		"authorUrl": "",
		"sourceUrl": ""
	},
	{
		"id": 139,
		"type": "door",
		"imgS": "",
		"imgL": "139.png",
		"degree": "",
		"name": "",
		"engName": "",
		"desc": "",
		"effect": "",
		"badStuff": "",
		"fightLevel": "",
		"reward": "",
		"class": "",
		"family": "",
		"lootSize": "",
		"lootType": "",
		"weaponType": "",
		"cost": "",
		"speciesRestriction": "",
		"damageKeys": "",
		"organicOrSynth": "",
		"skillType": "",
		"skillRank": "",
		"artAuthor": "",
		"artSource": "",
		"authorUrl": "",
		"sourceUrl": ""
	},
	{
		"id": 140,
		"type": "door",
		"imgS": "",
		"imgL": "140.png",
		"degree": "",
		"name": "",
		"engName": "",
		"desc": "",
		"effect": "",
		"badStuff": "",
		"fightLevel": "",
		"reward": "",
		"class": "",
		"family": "",
		"lootSize": "",
		"lootType": "",
		"weaponType": "",
		"cost": "",
		"speciesRestriction": "",
		"damageKeys": "",
		"organicOrSynth": "",
		"skillType": "",
		"skillRank": "",
		"artAuthor": "",
		"artSource": "",
		"authorUrl": "",
		"sourceUrl": ""
	}
]